mlhub/PredictionModel.py
mlhub/__init__.py
mlhub/sa.json
mlhub_cli-0.4.0.dist-info/METADATA
mlhub_cli-0.4.0.dist-info/RECORD
mlhub_cli-0.4.0.dist-info/WHEEL
mlhub_cli-0.4.0.dist-info/entry_points.txt
mlhub_cli-0.4.0.dist-info/top_level.txt
