Metadata-Version: 2.1
Name: mlhub-cli
Version: 0.4.0
Summary: Mlhub CLI
Home-page: https://github.com/tsuberim/mlhub
Author: Matan Tsuberi
Author-email: tsuberim@gmail.com
License: GPL-3.0
Platform: UNKNOWN
Requires-Dist: PyInquirer (==1.0.2)
Requires-Dist: halo (==0.0.17)
Requires-Dist: google-cloud-storage (==1.12.0)
